respan/__init__.py
respan/constants/__init__.py
respan/constants/dataset_constants.py
respan/constants/evaluator_constants.py
respan/constants/experiment_constants.py
respan/constants/log_constants.py
respan/constants/prompt_constants.py
respan/datasets/__init__.py
respan/datasets/api.py
respan/evaluators/__init__.py
respan/evaluators/api.py
respan/experiments/__init__.py
respan/experiments/api.py
respan/logs/__init__.py
respan/logs/api.py
respan/prompts/README.md
respan/prompts/__init__.py
respan/prompts/api.py
respan/types/__init__.py
respan/types/dataset_types.py
respan/types/evaluator_types.py
respan/types/experiment_types.py
respan/types/generic_types.py
respan/types/log_types.py
respan/types/prompt_types.py
respan/users/__init__.py
respan/utils/__init__.py
respan/utils/base.py
respan/utils/client.py
respan/utils/mixins.py
respan_ai-2.0.0.dist-info/METADATA
respan_ai-2.0.0.dist-info/WHEEL
respan_ai-2.0.0.dist-info/RECORD
