Metadata-Version: 2.1
Name: respan-ai
Version: 2.0.0
Summary: A package that helps interacting with Respan monitoring, evaluation & user analytics APIs
License: Apache 2.0
Author: Respan
Author-email: team@respan.ai
Requires-Python: >3.9,<4.0
Classifier: License :: Other/Proprietary License
Classifier: Programming Language :: Python :: 3
Classifier: Programming Language :: Python :: 3.10
Classifier: Programming Language :: Python :: 3.11
Classifier: Programming Language :: Python :: 3.12
Requires-Dist: httpx (>=0.28.1,<0.29.0)
Requires-Dist: respan-sdk (>=1.0.0,<2.0.0)
